CYuyanJichujiaochengLellansin/README.md
CYuyanJichujiaochengLellansin/__init__.py
CYuyanJichujiaochengLellansin/__main__.py
CYuyanJichujiaochengLellansin/file.epub
CYuyanJichujiaochengLellansin/index.html
CYuyanJichujiaochengLellansin/css/__init__.py
CYuyanJichujiaochengLellansin/css/annotations.css
CYuyanJichujiaochengLellansin/css/main.css
CYuyanJichujiaochengLellansin/css/normalize.css
CYuyanJichujiaochengLellansin/css/popup.css
CYuyanJichujiaochengLellansin/font/__init__.py
CYuyanJichujiaochengLellansin/font/fontello.eot
CYuyanJichujiaochengLellansin/font/fontello.svg
CYuyanJichujiaochengLellansin/font/fontello.ttf
CYuyanJichujiaochengLellansin/font/fontello.woff
CYuyanJichujiaochengLellansin/img/__init__.py
CYuyanJichujiaochengLellansin/img/annotator-glyph-sprite.png
CYuyanJichujiaochengLellansin/img/annotator-icon-sprite.png
CYuyanJichujiaochengLellansin/img/apple-touch-icon.png
CYuyanJichujiaochengLellansin/img/cancelfullscreen.png
CYuyanJichujiaochengLellansin/img/close.png
CYuyanJichujiaochengLellansin/img/fullscreen.png
CYuyanJichujiaochengLellansin/img/loader.gif
CYuyanJichujiaochengLellansin/img/menu-icon.png
CYuyanJichujiaochengLellansin/img/save.png
CYuyanJichujiaochengLellansin/img/saved.png
CYuyanJichujiaochengLellansin/img/settings-s.png
CYuyanJichujiaochengLellansin/img/settings.png
CYuyanJichujiaochengLellansin/img/star.png
CYuyanJichujiaochengLellansin/js/__init__.py
CYuyanJichujiaochengLellansin/js/epub.js
CYuyanJichujiaochengLellansin/js/epub.min.js
CYuyanJichujiaochengLellansin/js/epub.min.map
CYuyanJichujiaochengLellansin/js/hooks.min.js
CYuyanJichujiaochengLellansin/js/hooks.min.map
CYuyanJichujiaochengLellansin/js/reader.js
CYuyanJichujiaochengLellansin/js/reader.js.map
CYuyanJichujiaochengLellansin/js/reader.min.js
CYuyanJichujiaochengLellansin/js/reader.min.map
CYuyanJichujiaochengLellansin/js/hooks/__init__.py
CYuyanJichujiaochengLellansin/js/hooks/extensions/__init__.py
CYuyanJichujiaochengLellansin/js/hooks/extensions/highlight.js
c_yuyan_jichujiaocheng_lellansin-2024.3.2.0.dist-info/METADATA
c_yuyan_jichujiaocheng_lellansin-2024.3.2.0.dist-info/WHEEL
c_yuyan_jichujiaocheng_lellansin-2024.3.2.0.dist-info/entry_points.txt
c_yuyan_jichujiaocheng_lellansin-2024.3.2.0.dist-info/top_level.txt
c_yuyan_jichujiaocheng_lellansin-2024.3.2.0.dist-info/RECORD
